Metadata-Version: 2.1
Name: glinux-welcome
Version: 53
Summary: Ethical research - dep confusion package. This is not a real package, do not install.
